tocson_mcp_server/__init__.py
tocson_mcp_server-0.1.1.dist-info/METADATA
tocson_mcp_server-0.1.1.dist-info/WHEEL
tocson_mcp_server-0.1.1.dist-info/entry_points.txt
tocson_mcp_server-0.1.1.dist-info/RECORD
