Metadata-Version: 2.4
Name: tocson-mcp-server
Version: 0.1.1
Summary: Add your description here
Author-email: tocson <aiyina88@qq.com>
Requires-Python: >=3.13
Requires-Dist: mcp[cli]>=1.11.0
